youtupy/__init__.py
youtupy/main.py
youtupy/.system/imports.py
youtupy/.system/index.py
youtupy/.system/modules/-placeholder
youtupy/.system/sources/chars.yml
youtupy/.system/sources/clight.json
youtupy/.system/sources/logo.ico
youtupy-1.0.2.dist-info/licenses/LICENSE
youtupy-1.0.2.dist-info/METADATA
youtupy-1.0.2.dist-info/WHEEL
youtupy-1.0.2.dist-info/entry_points.txt
youtupy-1.0.2.dist-info/top_level.txt
youtupy-1.0.2.dist-info/RECORD
