Metadata-Version: 2.4
Name: youtupy
Version: 1.0.2
Summary: By using YouTuPy, you can download entire playlists or specific videos as .mp4 video files or .mp3 audio files.
Home-page: https://github.com/IG-onGit/YouTuPy
Author: Irakli Gzirishvili
Author-email: gziraklirex@gmail.com
Classifier: Programming Language :: Python :: 3
Classifier: License :: OSI Approved :: MIT License
Classifier: Operating System :: OS Independent
License-File: LICENSE
Requires-Dist: clight
Requires-Dist: yt-dlp
Requires-Dist: imageio-ffmpeg
Requires-Dist: yt_dlp
Requires-Dist: imageio_ffmpeg
Dynamic: author
Dynamic: author-email
Dynamic: classifier
Dynamic: description
Dynamic: description-content-type
Dynamic: home-page
Dynamic: license-file
Dynamic: requires-dist
Dynamic: summary
